Metadata-Version: 2.1
Name: example-pkg-lib2-LeoK
Version: 0.0.2
Summary: initial package try
Home-page: https://github.com/pypa/sampleproject
Author: Anonymous
Author-email: fffnox@gmail.com
License: UNKNOWN
Platform: UNKNOWN
Classifier: Programming Language :: Python :: 3
Classifier: License :: OSI Approved :: MIT License
Classifier: Operating System :: OS Independent
Requires-Python: >=3.6
